oceanxbridgeplatformapis/__init__.py
oceanxbridgeplatformapis/api_helper.py
oceanxbridgeplatformapis/configuration.py
oceanxbridgeplatformapis/oceanxbridgeplatformapis_client.py
oceanxbridgeplatformapis/controllers/__init__.py
oceanxbridgeplatformapis/controllers/base_controller.py
oceanxbridgeplatformapis/controllers/inventory_controller.py
oceanxbridgeplatformapis/controllers/products_controller.py
oceanxbridgeplatformapis/controllers/shipments_controller.py
oceanxbridgeplatformapis/controllers/webhooks_controller.py
oceanxbridgeplatformapis/exceptions/__init__.py
oceanxbridgeplatformapis/exceptions/api_exception.py
oceanxbridgeplatformapis/exceptions/error_responses_exception.py
oceanxbridgeplatformapis/exceptions/response_inv_tran_400_exception.py
oceanxbridgeplatformapis/http/__init__.py
oceanxbridgeplatformapis/http/http_call_back.py
oceanxbridgeplatformapis/http/http_method_enum.py
oceanxbridgeplatformapis/http/http_request.py
oceanxbridgeplatformapis/http/http_response.py
oceanxbridgeplatformapis/http/auth/__init__.py
oceanxbridgeplatformapis/http/auth/o_auth_2.py
oceanxbridgeplatformapis/models/__init__.py
oceanxbridgeplatformapis/models/address.py
oceanxbridgeplatformapis/models/asn_create_request.py
oceanxbridgeplatformapis/models/asn_product.py
oceanxbridgeplatformapis/models/asn_response.py
oceanxbridgeplatformapis/models/asn_response_product.py
oceanxbridgeplatformapis/models/asn_shipment.py
oceanxbridgeplatformapis/models/asn_shipment_mode_enum.py
oceanxbridgeplatformapis/models/asn_shipment_type_enum.py
oceanxbridgeplatformapis/models/asn_status_enum.py
oceanxbridgeplatformapis/models/asn_update_request.py
oceanxbridgeplatformapis/models/asnuom_enum.py
oceanxbridgeplatformapis/models/availability_enum.py
oceanxbridgeplatformapis/models/carrier_name_enum.py
oceanxbridgeplatformapis/models/component.py
oceanxbridgeplatformapis/models/component_option.py
oceanxbridgeplatformapis/models/custom_option.py
oceanxbridgeplatformapis/models/custom_option_1.py
ocean_x_package_sdk-1.3.0.dist-info/LICENSE
ocean_x_package_sdk-1.3.0.dist-info/METADATA
ocean_x_package_sdk-1.3.0.dist-info/WHEEL
ocean_x_package_sdk-1.3.0.dist-info/top_level.txt
ocean_x_package_sdk-1.3.0.dist-info/RECORD
